MANIFEST.in
README.md
setup.py
contextmenuwidget/__init__.py
contextmenuwidget/contextmenuwidget.py
contextmenuwidget.egg-info/PKG-INFO
contextmenuwidget.egg-info/SOURCES.txt
contextmenuwidget.egg-info/dependency_links.txt
contextmenuwidget.egg-info/top_level.txt
contextmenuwidget/Assets/Images/edit-copy.png
contextmenuwidget/Assets/Images/edit-cut.png
contextmenuwidget/Assets/Images/edit-paste.png
contextmenuwidget/Assets/Images/edit-redo.png
contextmenuwidget/Assets/Images/edit-select-all.png
contextmenuwidget/Assets/Images/edit-undo.png