Metadata-Version: 2.1
Name: contextmenuwidget
Version: 1.0.5
Summary: Extended widget with a context menu for tkinter, including Cut, Copy, and Paste commands.
Home-page: UNKNOWN
Author: Diablo76
Author-email: el_diablo76@msn.com
License: UNKNOWN
Keywords: tkinter context-menu cut copy paste
Platform: Windows
Platform: Linux
Platform: MacOS
Classifier: Development Status :: 5 - Production/Stable
Classifier: License :: OSI Approved :: MIT License
Classifier: Programming Language :: Python :: 3
Classifier: Operating System :: Microsoft :: Windows
Classifier: Operating System :: POSIX :: Linux
Classifier: Operating System :: MacOS
